{
  "$schema": "https://biomejs.dev/schemas/2.4.10/schema.json",
  "linter": {
    "enabled": true,
    "rules": {
      "recommended": true,
      "complexity": {
        "noForEach": "off"
      },
      "suspicious": {
        "noExplicitAny": "off",
        "useIterableCallbackReturn": "off",
        "noAssignInExpressions": "off",
        "noAsyncPromiseExecutor": "off",
        "noImplicitAnyLet": "off"
      },
      "correctness": {
        "noUnusedVariables": "warn",
        "noInnerDeclarations": "off"
      },
      "style": {
        "noNonNullAssertion": "off",
        "useNodejsImportProtocol": "off"
      }
    }
  },
  "formatter": {
    "enabled": true,
    "indentStyle": "space",
    "indentWidth": 2,
    "lineWidth": 120
  },
  "files": {
    "includes": ["src/**/*.ts", "*.json"]
  }
}
